Metadata-Version: 2.1
Name: gura
Version: 1.4.2
Summary: A Gura format parser
Home-page: https://github.com/gura-conf/gura-python-parser
Author: JWare
Author-email: jware.organization@gmail.com
License: MIT
Download-URL: https://github.com/gura-conf/gura-python-parser/archive/refs/tags/1.4.2.tar.gz
Keywords: Gura,parser,loads,dumps,encode,decode
Platform: UNKNOWN
Classifier: Development Status :: 5 - Production/Stable
Classifier: Intended Audience :: Developers
Classifier: Topic :: Software Development :: Build Tools
Classifier: License :: OSI Approved :: MIT License
Classifier: Programming Language :: Python :: 3
Classifier: Programming Language :: Python :: 3.4
Classifier: Programming Language :: Python :: 3.5
Classifier: Programming Language :: Python :: 3.6
Classifier: Programming Language :: Python :: 3.7
Classifier: Programming Language :: Python :: 3.8
Classifier: Programming Language :: Python :: 3.9
License-File: LICENSE
